qbz95/__init__.py
qbz95/config.py
qbz95/env.py
qbz95/chat/__init__.py
qbz95/chat/insuranceqa_test.py
qbz95/chat/insuranceqa_test1.py
qbz95/chat/chatterbot/__init__.py
qbz95/chat/chatterbot/chatter_bot1.py
qbz95/chat/chatterbot/chatterbot_example.py
qbz95/chat/chatterbot/sanic_example.py
qbz95/chat/chatterbot/flask/__init__.py
qbz95/chat/chatterbot/flask/app.py
qbz95/conf/__init__.py
qbz95/conf/config_base.py
qbz95/conf/config_jupyter.py
qbz95/docker/__init__.py
qbz95/docker/compose-example/__init__.py
qbz95/docker/compose-example/compose-app.py
qbz95/match/__init__.py
qbz95/match/ali_nlp/__init__.py
qbz95/ml/ObjectExample.py
qbz95/ml/__init__.py
qbz95/ml/linear_model.py
qbz95/ml/model.py
qbz95/ml/neural_network.py
qbz95/ml/planar_utils.py
qbz95/ml/predictor.py
qbz95/ml/utils.py
qbz95/ml2/__init__.py
qbz95/ml2/estimator.py
qbz95/ml2/initializer.py
qbz95/ml2/keras_gensim_embeddings.py
qbz95/ml2/layer.py
qbz95/ml2/network.py
qbz95/ml2/optimizer.py
qbz95/ml2/predictor.py
qbz95/ml2/regularizer.py
qbz95/ml2/utils.py
qbz95/ml3/__init__.py
qbz95/ml3/utils/__init__.py
qbz95/ml3/utils/data_helper.py
qbz95/rl/__init__.py
qbz95/rl/gym_1.py
qbz95/rl/gym_2.py
qbz95/rl/gym_3.py
qbz95/rl/mab.py
qbz95/rl/bandit/__init__.py
qbz95/rl/bandit/bandit.py
qbz95/rl/bandit/delay_epsilon_bandit.py
qbz95/rl/bandit/epsilon_greedy_bandit.py
qbz95/rl/bandit/multi_armed_bandit.py
qbz95/rl/bandit/thompson_sampling_bandit.py
qbz95/rl/bandit/ucb_bandit.py
qbz95/rl/bandit/upper_limit_bandit.py
qbz95/tests/__init__.py
qbz95/tests/temp.py
qbz95/tests/ml/__init__.py
qbz95/tests/ml/testCases_v2.py
qbz95/tests/ml/test_LinearRegression.py
qbz95/tests/ml/test_LogisticRegression.py
qbz95/tests/ml/test_NeuralNetwork.py
qbz95/tests/ml/test_Predictor.py
qbz95/tests/ml/test_utils.py
qbz95/tests/ml2/__init__.py
qbz95/tests/ml2/test_Estimator.py
qbz95/tests/ml2/test_Layer.py
qbz95/tests/ml2/test_PandasHelper.py
qbz95/tf/__init__.py
qbz95/tf/code_test.py
qbz95/tf/keras.py
qbz95/tf/mnist_with_summaries.py
qbz95-0.0.1.dist-info/LICENSE
qbz95-0.0.1.dist-info/METADATA
qbz95-0.0.1.dist-info/WHEEL
qbz95-0.0.1.dist-info/top_level.txt
qbz95-0.0.1.dist-info/RECORD
