Metadata-Version: 2.1
Name: qbz95
Version: 0.0.1
Summary: a machine learning library which collects my experience on AI.
Home-page: https://github.com/xuxiangwen/qbz95
Author: eipi10
Author-email: eipi10@qq.com
License: UNKNOWN
Platform: UNKNOWN
Classifier: Programming Language :: Python :: 3
Classifier: License :: OSI Approved :: MIT License
Classifier: Operating System :: OS Independent
